llmlinks/__init__.py
llmlinks/compiler.py
llmlinks/link.py
llmlinks/llm_client.py
llmlinks/llm/__init__.py
llmlinks/llm/anthropic_model.py
llmlinks/llm/google_model.py
llmlinks/llm/openai_model.py
llmlinks/parser/__init__.py
llmlinks/parser/xml.py
llmlinks-0.1.34.dist-info/LICENSE
llmlinks-0.1.34.dist-info/METADATA
llmlinks-0.1.34.dist-info/WHEEL
llmlinks-0.1.34.dist-info/top_level.txt
llmlinks-0.1.34.dist-info/RECORD
