Metadata-Version: 2.1
Name: llmlinks
Version: 0.1.34
Summary: Add your description here
Requires-Python: >=3.10
License-File: LICENSE
Requires-Dist: anthropic >=0.34.2
Requires-Dist: google-generativeai >=0.8.2
Requires-Dist: openai >=1.50.2
Requires-Dist: tomli-w >=1.0.0
Requires-Dist: tomli >=2.0.1
